Metadata-Version: 2.1
Name: utils-email-package
Version: 0.0.1
Summary: Utils for email
Author: triandn43
Author-email: triandn43@gmail.com
Classifier: Programming Language :: Python :: 2
Classifier: License :: OSI Approved :: MIT License
Classifier: Operating System :: OS Independent
